{
    "Mammal": {
        "might": 10,
        "endurance": 11,
        "finesse": 12,
        "reflexes": 9,
        "vitality": 10,
        "fortitude": 8,
        "knowledge": 12,
        "logic": 8,
        "awareness": 9,
        "intuition": 10,
        "charm": 11,
        "willpower": 10
    },
    "Avian": {
        "might": 8,
        "endurance": 10,
        "finesse": 10,
        "reflexes": 12,
        "vitality": 11,
        "fortitude": 9,
        "knowledge": 11,
        "logic": 9,
        "awareness": 12,
        "intuition": 8,
        "charm": 10,
        "willpower": 10
    },
    "Reptile": {
        "might": 10,
        "endurance": 9,
        "finesse": 8,
        "reflexes": 11,
        "vitality": 10,
        "fortitude": 12,
        "knowledge": 10,
        "logic": 12,
        "awareness": 8,
        "intuition": 11,
        "charm": 10,
        "willpower": 9
    },
    "Insect": {
        "might": 12,
        "endurance": 8,
        "finesse": 10,
        "reflexes": 10,
        "vitality": 9,
        "fortitude": 11,
        "knowledge": 10,
        "logic": 11,
        "awareness": 10,
        "intuition": 12,
        "charm": 9,
        "willpower": 8
    },
    "Aquatic": {
        "might": 9,
        "endurance": 12,
        "finesse": 11,
        "reflexes": 10,
        "vitality": 8,
        "fortitude": 10,
        "knowledge": 9,
        "logic": 10,
        "awareness": 11,
        "intuition": 10,
        "charm": 8,
        "willpower": 12
    },
    "Plant": {
        "might": 11,
        "endurance": 10,
        "finesse": 9,
        "reflexes": 8,
        "vitality": 12,
        "fortitude": 10,
        "knowledge": 8,
        "logic": 10,
        "awareness": 10,
        "intuition": 9,
        "charm": 12,
        "willpower": 11
    }
}